voice_annotation_tool/__init__.py
voice_annotation_tool/__main__.py
voice_annotation_tool/about_dialog.py
voice_annotation_tool/annotation.py
voice_annotation_tool/annotation_list_model.py
voice_annotation_tool/application.py
voice_annotation_tool/audio_playback_widget.py
voice_annotation_tool/choose_project_frame.py
voice_annotation_tool/main.py
voice_annotation_tool/main_window.py
voice_annotation_tool/opened_project_frame.py
voice_annotation_tool/project.py
voice_annotation_tool/project_settings_dialog.py
voice_annotation_tool/shortcut_settings_dialog.py
voice_annotation_tool/shortcut_widget.py
voice_annotation_tool-1.9.0.dist-info/LICENSE
voice_annotation_tool-1.9.0.dist-info/METADATA
voice_annotation_tool-1.9.0.dist-info/WHEEL
voice_annotation_tool-1.9.0.dist-info/entry_points.txt
voice_annotation_tool-1.9.0.dist-info/top_level.txt
voice_annotation_tool-1.9.0.dist-info/RECORD
