Metadata-Version: 2.1
Name: voice-annotation-tool
Version: 1.9.0
Summary: Utility to annotate short voice samples
Home-page: https://github.com/tud-zih-energy/voice-annotation-tool
Author: Feliks Weber
Author-email: feliks.weber@tu-dresden.de
Project-URL: Bug Tracker, https://github.com/tud-zih-energy/voice-annotation-tool/issues
Project-URL: Documentation, https://voice-annotation-tool.readthedocs.io/en/latest/
Classifier: Programming Language :: Python :: 3
Classifier: License :: OSI Approved :: GNU General Public License v3 (GPLv3)
Classifier: Operating System :: OS Independent
Classifier: Topic :: Multimedia :: Sound/Audio :: Speech
Classifier: Natural Language :: English
Classifier: Natural Language :: German
Classifier: Typing :: Typed
Classifier: Intended Audience :: Science/Research
Requires-Python: >=3.9
License-File: LICENSE
Requires-Dist: PySide6 (>=6.2.2.1)
Requires-Dist: shiboken6 (>=6.2.2.1)
